configparsersimplifier
