Metadata-Version: 2.1
Name: configparsersimplifier
Version: 1.2
Summary: Simplifying work with configparser.
Author: lamefate
Author-email: 0xETHER.000@protonmail.com
